slmgen/__init__.py
slmgen/__main__.py
slmgen/luts.py
slmgen/makepsf.py
slmgen/slm.py
slmgen/slm_pattern_dialog.py
slmgen/slm_pattern_dialog.ui
slmgen/slmgen_logo.png
slmgen/slmwindow.py
llspy_slm-0.2.1.dist-info/LICENSE
llspy_slm-0.2.1.dist-info/METADATA
llspy_slm-0.2.1.dist-info/WHEEL
llspy_slm-0.2.1.dist-info/entry_points.txt
llspy_slm-0.2.1.dist-info/top_level.txt
llspy_slm-0.2.1.dist-info/RECORD
