Metadata-Version: 2.1
Name: llspy-slm
Version: 0.2.1
Summary: Lattice Light Sheet SLM Pattern Generator
Home-page: https://github.com/tlambert03/llspy-slm
Author: Talley Lambert
Author-email: talley.lambert@gmail.com
License: BSD 3-clause
Platform: UNKNOWN
Classifier: Development Status :: 3 - Alpha
Classifier: Intended Audience :: Science/Research
Classifier: License :: OSI Approved :: BSD License
Classifier: Natural Language :: English
Classifier: Operating System :: MacOS
Classifier: Operating System :: Microsoft :: Windows
Classifier: Operating System :: POSIX :: Linux
Classifier: Programming Language :: Python
Classifier: Programming Language :: Python :: 3
Classifier: Programming Language :: Python :: 3.7
Classifier: Programming Language :: Python :: 3.8
Classifier: Programming Language :: Python :: 3.9
Classifier: Programming Language :: Python :: 3.10
Classifier: Topic :: Scientific/Engineering
Classifier: Topic :: Scientific/Engineering :: Visualization
Requires-Python: >=3.7
License-File: LICENSE
Requires-Dist: numpy
Requires-Dist: scipy
Requires-Dist: pillow
Requires-Dist: qtpy
Requires-Dist: numba ; python_version < "3.10"
Provides-Extra: tests
Requires-Dist: pytest ; extra == 'tests'
Requires-Dist: pytest-qt ; extra == 'tests'
Requires-Dist: pyqt5 ; extra == 'tests'
Requires-Dist: pytest-cov ; extra == 'tests'
